pyfinn/__init__.py
pyfinn/api.py
pyfinn-0.1.0.dist-info/LICENSE
pyfinn-0.1.0.dist-info/WHEEL
pyfinn-0.1.0.dist-info/METADATA
pyfinn-0.1.0.dist-info/RECORD
