Metadata-Version: 2.1
Name: pyfinn
Version: 0.1.0
Summary: Fetch real estate listing from finn.no and make available as JSON
License: MIT
Author: Nikolai R Kristiansen
Author-email: nikolaik@gmail.com
Requires-Python: >=3.8,<4
Classifier: License :: OSI Approved :: MIT License
Classifier: Programming Language :: Python :: 3
Classifier: Programming Language :: Python :: 3.10
Classifier: Programming Language :: Python :: 3.8
Classifier: Programming Language :: Python :: 3.9
Requires-Dist: fake-useragent
Requires-Dist: flask
Requires-Dist: gunicorn
Requires-Dist: redis
Requires-Dist: requests-html
Requires-Dist: urllib3 (>=1.24.2)
